dbt_table_diff/__init__.py
dbt_table_diff/__main__.py
dbt_table_diff/arg_parser.py
dbt_table_diff/run_sql_checks.py
dbt_table_diff-2.2.3.dist-info/LICENSE
dbt_table_diff-2.2.3.dist-info/METADATA
dbt_table_diff-2.2.3.dist-info/WHEEL
dbt_table_diff-2.2.3.dist-info/top_level.txt
dbt_table_diff-2.2.3.dist-info/RECORD
