Metadata-Version: 2.1
Name: dbt-table-diff
Version: 2.2.3
Summary: Compares models in dbt during an open PR
Home-page: https://github.com/org-not-included/dbt_table_diff/
Author: mtsadler (Mike Sadler)
Author-email: <michaeltsadler1@gmail.com>
Keywords: bigquery,qa,sql,table,comment,check,Pull Request,dbt,cicd
Classifier: Intended Audience :: Developers
Classifier: Programming Language :: Python :: 3
Classifier: Operating System :: Unix
Classifier: Operating System :: MacOS :: MacOS X
Classifier: Operating System :: Microsoft :: Windows
License-File: LICENSE
Requires-Dist: dbt-bigquery (==1.0.0)
Requires-Dist: google-cloud-bigquery (==2.34.4)
Requires-Dist: jinja2 (==2.11.3)
Requires-Dist: markupsafe (==2.0.1)
Requires-Dist: pandas (==1.4.3)
Requires-Dist: pandas-gbq (==0.17.8)
Requires-Dist: py-github-helper (>=0.2.2)
